gmssl/__init__.py
gmssl/func.py
gmssl/sm2.py
gmssl/sm3.py
gmssl/sm4.py
gmssl_fix-0.0.1.dist-info/METADATA
gmssl_fix-0.0.1.dist-info/WHEEL
gmssl_fix-0.0.1.dist-info/top_level.txt
gmssl_fix-0.0.1.dist-info/RECORD
