Metadata-Version: 2.1
Name: gmssl_fix
Version: 0.0.1
Summary: Pure-Python SM2/SM3/SM4 implementation, fork https://github.com/duanhongyi/gmssl, fix when publickey is 64 bytes 04 begin sign bug.
Home-page: https://github.com/kongber/gmssl_fix
Author: kongber
Author-email: 206793787@qq.com
License: BSD
Platform: all platform
Requires-Dist: pycryptodomex
